{
  "levels": [
    {
      "name": "Bronze",
      "minPoints": 0,
      "maxPoints": 999,
      "color": "#CD7F32",
      "icon": "🥉",
      "benefits": ["Acceso básico a la tienda", "Reseñas de productos"]
    },
    {
      "name": "Silver",
      "minPoints": 1000,
      "maxPoints": 2499,
      "color": "#C0C0C0",
      "icon": "🥈",
      "benefits": [
        "5% descuento en compras",
        "Acceso anticipado a ofertas",
        "Soporte prioritario"
      ]
    },
    {
      "name": "Gold",
      "minPoints": 2500,
      "maxPoints": 4999,
      "color": "#FFD700",
      "icon": "🥇",
      "benefits": [
        "10% descuento en compras",
        "Envío gratis en todos los pedidos",
        "Acceso a productos exclusivos",
        "Chat VIP con soporte"
      ]
    },
    {
      "name": "Platinum",
      "minPoints": 5000,
      "maxPoints": null,
      "color": "#E5E4E2",
      "icon": "💎",
      "benefits": [
        "15% descuento en compras",
        "Envío express gratuito",
        "Acceso a eventos exclusivos",
        "Representante personal de cuenta",
        "Early access a nuevos productos"
      ]
    }
  ],
  "pointsPerPurchase": {
    "baseMultiplier": 1,
    "rules": [
      {
        "minAmount": 0,
        "pointsPerPeso": 0.1
      },
      {
        "minAmount": 50000,
        "pointsPerPeso": 0.15,
        "description": "Bonus por compras mayores a $50.000"
      },
      {
        "minAmount": 100000,
        "pointsPerPeso": 0.2,
        "description": "Bonus por compras mayores a $100.000"
      }
    ]
  }
}
